{
  "_fv": 79,
  "_type": "gui",
  "definition": {
    "type": 1,
    "width": 375,
    "height": 200,
    "inventoryOffsetX": 0,
    "inventoryOffsetY": 150,
    "renderBgLayer": true,
    "doesPauseGame": false,
    "components": [
      {
        "type": "outputslot",
        "data": {
          "id": 0,
          "disablePickup": {
            "fixedValue": false
          },
          "dropItemsWhenNotBound": false,
          "onTakenFromSlot": {
            "name": "Competense01"
          },
          "x": 204,
          "y": 26,
          "locked": false
        }
      },
      {
        "type": "outputslot",
        "data": {
          "id": 1,
          "disablePickup": {
            "fixedValue": false
          },
          "dropItemsWhenNotBound": false,
          "onTakenFromSlot": {
            "name": "Competense02"
          },
          "x": 132,
          "y": 53,
          "locked": false
        }
      },
      {
        "type": "outputslot",
        "data": {
          "id": 2,
          "disablePickup": {
            "fixedValue": false
          },
          "dropItemsWhenNotBound": false,
          "onTakenFromSlot": {
            "name": "Competense03"
          },
          "x": 204,
          "y": 62,
          "locked": false
        }
      },
      {
        "type": "outputslot",
        "data": {
          "id": 3,
          "disablePickup": {
            "fixedValue": false
          },
          "dropItemsWhenNotBound": false,
          "onTakenFromSlot": {
            "name": "Competense04"
          },
          "x": 177,
          "y": 98,
          "locked": false
        }
      },
      {
        "type": "outputslot",
        "data": {
          "id": 4,
          "disablePickup": {
            "fixedValue": false
          },
          "dropItemsWhenNotBound": false,
          "onTakenFromSlot": {
            "name": "Competense05"
          },
          "x": 177,
          "y": 134,
          "locked": false
        }
      },
      {
        "type": "outputslot",
        "data": {
          "id": 5,
          "disablePickup": {
            "fixedValue": false
          },
          "dropItemsWhenNotBound": false,
          "onTakenFromSlot": {
            "name": "Competense06"
          },
          "x": 231,
          "y": 98,
          "locked": false
        }
      },
      {
        "type": "outputslot",
        "data": {
          "id": 6,
          "disablePickup": {
            "fixedValue": false
          },
          "dropItemsWhenNotBound": false,
          "onTakenFromSlot": {
            "name": "Competense07"
          },
          "x": 60,
          "y": 53,
          "locked": false
        }
      },
      {
        "type": "outputslot",
        "data": {
          "id": 7,
          "disablePickup": {
            "fixedValue": false
          },
          "dropItemsWhenNotBound": false,
          "onTakenFromSlot": {
            "name": "Competense08"
          },
          "x": 60,
          "y": 89,
          "locked": false
        }
      },
      {
        "type": "outputslot",
        "data": {
          "id": 8,
          "disablePickup": {
            "fixedValue": false
          },
          "dropItemsWhenNotBound": false,
          "onTakenFromSlot": {
            "name": "Competense09"
          },
          "x": 60,
          "y": 125,
          "locked": false
        }
      },
      {
        "type": "outputslot",
        "data": {
          "id": 9,
          "disablePickup": {
            "fixedValue": false
          },
          "dropItemsWhenNotBound": false,
          "onTakenFromSlot": {
            "name": "Competense10"
          },
          "x": 276,
          "y": 53,
          "locked": false
        }
      },
      {
        "type": "outputslot",
        "data": {
          "id": 10,
          "disablePickup": {
            "fixedValue": false
          },
          "dropItemsWhenNotBound": false,
          "onTakenFromSlot": {
            "name": "Competense11"
          },
          "x": 303,
          "y": 89,
          "locked": false
        }
      },
      {
        "type": "image",
        "data": {
          "image": "qerzft.png",
          "use1Xscale": false,
          "x": 26,
          "y": 20,
          "locked": false
        }
      },
      {
        "type": "label",
        "data": {
          "name": "label_page_1",
          "text": {
            "fixedValue": "page 1"
          },
          "color": {
            "value": -12829636,
            "falpha": 0.0
          },
          "x": 357,
          "y": 26,
          "locked": false
        }
      },
      {
        "type": "button",
        "data": {
          "name": "button_page_2",
          "text": "page 2",
          "isUndecorated": false,
          "onClick": {
            "name": "Opencomp2"
          },
          "width": 56,
          "height": 20,
          "x": 339,
          "y": 188,
          "locked": false
        }
      },
      {
        "type": "label",
        "data": {
          "name": "label_proc_variableskills",
          "text": {
            "fixedValue": "",
            "name": "Variableskills"
          },
          "color": {
            "value": -12829636,
            "falpha": 0.0
          },
          "x": 33,
          "y": 26,
          "locked": false
        }
      }
    ],
    "onTick": {
      "name": "CompetensesPendantQueCeGUIEstOuvertParTick"
    },
    "gridSettings": {
      "sx": 18,
      "sy": 18,
      "ox": 11,
      "oy": 15,
      "snapOnGrid": true
    }
  }
}